<?xml version="1.0" encoding="UTF-8"?>
<con:resource name="/api/v1/Series/{id}/completestep" path="/api/v1/Series/{id}/completestep" id="e975f7e4-08b5-437e-90e5-0d2dd7d444f1" xmlns:xsi="http://www.w3.org/2001/XMLSchema-instance" xmlns:con="http://eviware.com/soapui/config"><con:settings><con:setting id="e975f7e4-08b5-437e-90e5-0d2dd7d444f1fileName">%2Fapi%2Fv1%2FSeries%2F%7Bid%7D%2Fcompletestep</con:setting></con:settings><con:parameters><con:parameter required="true"><con:name>id</con:name><con:style>TEMPLATE</con:style><con:description xsi:nil="true"/></con:parameter></con:parameters><con:method name="ApiV1SeriesByIdCompletestepPost" id="f5a4699b-9705-4f3d-89dc-7541db70cdce" method="POST"><con:description>
</con:description><con:settings/><con:parameters><con:parameter><con:name>currentStepId</con:name><con:style>QUERY</con:style><con:description xsi:nil="true"/></con:parameter><con:parameter><con:name>ignoreMultiModality</con:name><con:style>QUERY</con:style><con:description xsi:nil="true"/></con:parameter><con:parameter><con:name>receivedLaterality</con:name><con:style>QUERY</con:style><con:description xsi:nil="true"/></con:parameter><con:parameter><con:name>password</con:name><con:style>HEADER</con:style><con:description xsi:nil="true"/></con:parameter></con:parameters><con:representation type="RESPONSE"><con:mediaType>application/json</con:mediaType><con:status>200</con:status><con:params/></con:representation><con:request name="Request 1" id="dec97ae5-d3e4-4e23-96a2-6188433c6b4e" mediaType="application/json"><con:settings/><con:request/><con:credentials><con:selectedAuthProfile>No Authorization</con:selectedAuthProfile><con:authType>No Authorization</con:authType></con:credentials><con:jmsConfig JMSDeliveryMode="PERSISTENT"/><con:parameters/></con:request></con:method></con:resource>