<?xml version="1.0" encoding="UTF-8"?>
<con:resource name="/api/v1/Common/GetCountries" path="/api/v1/Common/GetCountries" id="3ded8e38-558e-448a-9583-9d8f8050f0f1" xmlns:xsi="http://www.w3.org/2001/XMLSchema-instance" xmlns:con="http://eviware.com/soapui/config"><con:settings><con:setting id="3ded8e38-558e-448a-9583-9d8f8050f0f1fileName">%2Fapi%2Fv1%2FCommon%2FGetCountries</con:setting></con:settings><con:parameters/><con:method name="ApiV1CommonGetCountriesGet" id="e97822f0-4fd3-4a0e-bad6-b1e63ac80131" method="GET"><con:description>
</con:description><con:settings/><con:parameters/><con:representation type="RESPONSE"><con:mediaType>application/json</con:mediaType><con:status>200</con:status><con:params/></con:representation><con:request name="Request 1" id="ea864faf-b418-44d3-acb8-a97cbae9f293" mediaType="application/json"><con:settings/><con:request/><con:credentials><con:selectedAuthProfile>No Authorization</con:selectedAuthProfile><con:authType>No Authorization</con:authType></con:credentials><con:jmsConfig JMSDeliveryMode="PERSISTENT"/><con:parameters/></con:request></con:method></con:resource>