<?xml version="1.0" encoding="UTF-8"?>
<con:resource name="/api/v1/TemplateQuestions/{id}/validation" path="/api/v1/TemplateQuestions/{id}/validation" id="56c752a4-fac5-4a87-a9df-c51a11304dfb" xmlns:xsi="http://www.w3.org/2001/XMLSchema-instance" xmlns:con="http://eviware.com/soapui/config"><con:settings><con:setting id="56c752a4-fac5-4a87-a9df-c51a11304dfbfileName">%2Fapi%2Fv1%2FTemplateQuestions%2F%7Bid%7D%2Fvalidation</con:setting></con:settings><con:parameters><con:parameter required="true"><con:name>id</con:name><con:style>TEMPLATE</con:style><con:description xsi:nil="true"/></con:parameter></con:parameters><con:method name="ApiV1TemplateQuestionsByIdValidationPost" id="f8302fd1-bb03-4efa-b2da-150b8c40370f" method="POST"><con:description>
</con:description><con:settings/><con:parameters/><con:representation type="REQUEST"><con:mediaType>application/json</con:mediaType><con:params/><con:sampleContent>{"description":"string","control":"string","mask":"string","max":"string","min":"string","tick":"string","toolTip":"string","unit":"string","study":{"otherDrugs":"string","protocolTitle":"string","phase":"string","arm":"string","diseaseType":"string","subjectSeg":"string","therapeuticClass":"string","locations":"string","subjectIdMask":"string","subjectAlternativeIdMask":"string","subjectNameCodeMask":"string","firstSubjectEnrollDate":"2015-07-20T15:49:04-07:00","lastSubjectEnrollDate":"2015-07-20T15:49:04-07:00","lastSubjectVisitDate":"2015-07-20T15:49:04-07:00","firstDataExportDate":"2015-07-20T15:49:04-07:00","lastDataExportDate":"2015-07-20T15:49:04-07:00","isValidated":true,"isSubjectNameCodeRequired":true,"isEligibilityIdUsed":true,"isCompletedPublic":true,"isTestingPhase":true,"isEligibilityCloningEnabled":true,"shouldEligibleLateralityBeDetermined":true,"isSubjectGenderRequired":true,"isSubjectBirthYearRequired":true,"alwaysVerifyMultipleGrades":true,"needCertification":true,"id":0,"name":"string","alias":"string","primaryDrugs":"string","isActive":true,"isLocked":true,"lockedDate":"2015-07-20T15:49:04-07:00","endDate":"2015-07-20T15:49:04-07:00","startDate":"2015-07-20T15:49:04-07:00","totalSubjects":0,"animalSpeciesId":0,"impressionId":0,"totalQueriesPending":0,"totalQueriesFlagged":0,"animalSpecies":{"id":0,"name":"string","displayName":"string"},"impression":{"id":0,"color":"string","description":"string"}},"id":0,"studyId":0,"name":"string","isActive":true}</con:sampleContent></con:representation><con:representation type="REQUEST"><con:mediaType>text/json</con:mediaType><con:params/><con:sampleContent/></con:representation><con:representation type="REQUEST"><con:mediaType>application/json-patch+json</con:mediaType><con:params/><con:sampleContent/></con:representation><con:representation type="RESPONSE"><con:mediaType>application/json</con:mediaType><con:status>200</con:status><con:params/></con:representation><con:representation type="REQUEST"><con:mediaType>application/json</con:mediaType><con:params/></con:representation><con:representation type="REQUEST"><con:mediaType>text/json</con:mediaType><con:params/></con:representation><con:representation type="REQUEST"><con:mediaType>application/json-patch+json</con:mediaType><con:params/></con:representation><con:request name="Request 1" id="cd43ebd7-a582-426b-94de-4a921caf0eeb" mediaType="application/json"><con:settings/><con:request>{"description":"string","control":"string","mask":"string","max":"string","min":"string","tick":"string","toolTip":"string","unit":"string","study":{"otherDrugs":"string","protocolTitle":"string","phase":"string","arm":"string","diseaseType":"string","subjectSeg":"string","therapeuticClass":"string","locations":"string","subjectIdMask":"string","subjectAlternativeIdMask":"string","subjectNameCodeMask":"string","firstSubjectEnrollDate":"2015-07-20T15:49:04-07:00","lastSubjectEnrollDate":"2015-07-20T15:49:04-07:00","lastSubjectVisitDate":"2015-07-20T15:49:04-07:00","firstDataExportDate":"2015-07-20T15:49:04-07:00","lastDataExportDate":"2015-07-20T15:49:04-07:00","isValidated":true,"isSubjectNameCodeRequired":true,"isEligibilityIdUsed":true,"isCompletedPublic":true,"isTestingPhase":true,"isEligibilityCloningEnabled":true,"shouldEligibleLateralityBeDetermined":true,"isSubjectGenderRequired":true,"isSubjectBirthYearRequired":true,"alwaysVerifyMultipleGrades":true,"needCertification":true,"id":0,"name":"string","alias":"string","primaryDrugs":"string","isActive":true,"isLocked":true,"lockedDate":"2015-07-20T15:49:04-07:00","endDate":"2015-07-20T15:49:04-07:00","startDate":"2015-07-20T15:49:04-07:00","totalSubjects":0,"animalSpeciesId":0,"impressionId":0,"totalQueriesPending":0,"totalQueriesFlagged":0,"animalSpecies":{"id":0,"name":"string","displayName":"string"},"impression":{"id":0,"color":"string","description":"string"}},"id":0,"studyId":0,"name":"string","isActive":true}</con:request><con:credentials><con:selectedAuthProfile>No Authorization</con:selectedAuthProfile><con:authType>No Authorization</con:authType></con:credentials><con:jmsConfig JMSDeliveryMode="PERSISTENT"/><con:parameters/></con:request><con:request name="Request 2" id="49999f79-40e7-4aeb-b583-b7076aa8ab6d" mediaType="text/json"><con:settings/><con:request/><con:credentials><con:selectedAuthProfile>No Authorization</con:selectedAuthProfile><con:authType>No Authorization</con:authType></con:credentials><con:jmsConfig JMSDeliveryMode="PERSISTENT"/><con:parameters/></con:request><con:request name="Request 3" id="9bd5c4aa-9e68-40e1-9091-e6746452c35c" mediaType="application/json-patch+json"><con:settings/><con:request/><con:credentials><con:selectedAuthProfile>No Authorization</con:selectedAuthProfile><con:authType>No Authorization</con:authType></con:credentials><con:jmsConfig JMSDeliveryMode="PERSISTENT"/><con:parameters/></con:request></con:method></con:resource>